{
  "id": "unit-analyze/unit-core",
  "name": "Unit Analyze/unit Core",
  "description": "7 files, primarily TypeScript",
  "files": [
    "src/cli/commands/next.ts",
    "src/core/next-task.ts",
    "tests/unit/core/feature-filtered-task.test.ts",
    "tests/unit/core/next-task-matching.test.ts",
    "tests/unit/core/next-task-scoring.test.ts",
    "tests/unit/core/next-task.test.ts",
    "tests/unit/core/requirements-prioritization.test.ts"
  ],
  "entryPoints": [
    "src/cli/commands/next.ts",
    "src/core/next-task.ts"
  ],
  "cohesion": 0.88,
  "coupling": 0.13,
  "fileCount": 7,
  "lineCount": 0
}
